ankidmpy/__init__.py
ankidmpy/__main__.py
ankidmpy/builder.py
ankidmpy/copier.py
ankidmpy/importer.py
ankidmpy/indexer.py
ankidmpy/runner.py
ankidmpy/templates/Default/Default.json
ankidmpy/util.py
ankidmpy-0.1.1.dist-info/entry_points.txt
ankidmpy-0.1.1.dist-info/LICENSE.md
ankidmpy-0.1.1.dist-info/WHEEL
ankidmpy-0.1.1.dist-info/METADATA
ankidmpy-0.1.1.dist-info/RECORD
