Metadata-Version: 2.1
Name: ankidmpy
Version: 0.1.1
Summary: Python port of github.com/OnkelTem/anki-dm
Home-page: https://github.com/gitonthescene/ankidmpy
License: MIT
Keywords: Anki,CrowdAnki,flash cards
Author: Douglas Mennella
Author-email: trx2358-pypi@yahoo.com
Requires-Python: >=3.7,<4.0
Classifier: License :: OSI Approved :: MIT License
Classifier: Programming Language :: Python :: 3
Classifier: Programming Language :: Python :: 3.7
Classifier: Programming Language :: Python :: 3.8
Project-URL: Repository, https://github.com/gitonthescene/ankidmpy
